{"frameRate":60,"name":"win","version":"5.5","compatibleVersion":"5.5","armature":[{"type":"Armature","frameRate":60,"name":"Armature","aabb":{"x":-321.7,"y":-321.16,"width":630.22,"height":257.67},"bone":[{"name":"root"},{"name":"cd01","parent":"root","transform":{"x":-243.3065,"y":-148.141}},{"name":"cd02","parent":"root","transform":{"x":198.0252,"y":-148.112}},{"name":"cd03","parent":"root","transform":{"x":-308.7023,"y":-260.9049}},{"name":"cd04","parent":"root","transform":{"x":-180.6641,"y":-300.0217}},{"name":"cd05","parent":"root","transform":{"x":190.9798,"y":-285.1172}},{"name":"cd06","parent":"root","transform":{"x":300.0217,"y":-142.6866}},{"name":"cd07","parent":"root","transform":{"x":-278.3203,"y":-69.987}},{"name":"cd08","parent":"root","transform":{"x":-243.3065,"y":-148.141}},{"name":"cd09","parent":"root","transform":{"x":-180.6641,"y":-300.0217}}],"slot":[{"name":"cd01","parent":"cd01"},{"name":"cd02","parent":"cd02"},{"name":"cd03","parent":"cd03"},{"name":"cd04","parent":"cd04"},{"name":"cd05","parent":"cd05"},{"name":"cd06","parent":"cd06"},{"name":"cd07","parent":"cd07"},{"name":"cd011","parent":"cd08"},{"name":"cd041","parent":"cd09"}],"skin":[{"slot":[{"name":"cd05","display":[{"name":"cd05","transform":{"x":0.21,"y":-1.04}}]},{"name":"cd041","display":[{"name":"cd04"}]},{"name":"cd06","display":[{"name":"cd06"}]},{"name":"cd01","display":[{"name":"cd01","transform":{"x":2.82,"y":0.4}}]},{"name":"cd07","display":[{"name":"cd07"}]},{"name":"cd03","display":[{"name":"cd03"}]},{"name":"cd04","display":[{"name":"cd04"}]},{"name":"cd011","display":[{"name":"cd01","transform":{"x":2.82,"y":0.4}}]},{"name":"cd02","display":[{"name":"cd02"}]}]}],"animation":[{"duration":60,"playTimes":0,"name":"newAnimation","bone":[{"name":"cd01","translateFrame":[{"duration":10,"tweenEasing":0,"x":82.16,"y":-13.26},{"duration":48,"tweenEasing":0,"x":82.16,"y":-13.26},{"duration":2,"x":-62.49,"y":57.16}],"rotateFrame":[{"duration":10},{"duration":48,"tweenEasing":0},{"duration":2,"rotate":-41.93}]},{"name":"cd02","translateFrame":[{"duration":32,"tweenEasing":0},{"duration":28,"x":79.29,"y":30.15}],"rotateFrame":[{"duration":32,"tweenEasing":0,"rotate":41.89},{"duration":28,"rotate":10.55}]},{"name":"cd03","translateFrame":[{"duration":54,"tweenEasing":0,"x":181.33,"y":82.04},{"duration":6,"x":20.01,"y":40.7}],"rotateFrame":[{"duration":54,"tweenEasing":0},{"duration":6,"rotate":42.84}]},{"name":"cd04","translateFrame":[{"duration":33,"tweenEasing":0,"x":79.38,"y":60.55},{"duration":27,"x":-27.64,"y":-38.6}]},{"name":"cd05","translateFrame":[{"duration":51,"tweenEasing":0,"x":-54.23,"y":76.14},{"duration":9,"x":67.2,"y":-1.42}],"rotateFrame":[{"duration":51,"tweenEasing":0,"rotate":-32.78},{"duration":9}],"scaleFrame":[{"duration":51,"tweenEasing":0,"x":0.8,"y":0.8},{"duration":9}]},{"name":"cd06","translateFrame":[{"duration":51,"tweenEasing":0,"x":-71.99,"y":-109.7},{"duration":9,"x":17.22,"y":-76.66}]},{"name":"cd07","translateFrame":[{"duration":12,"tweenEasing":0,"x":243.68,"y":-103.75},{"duration":47,"tweenEasing":0,"x":243.68,"y":-103.75},{"x":190.83,"y":-69.77}]},{"name":"cd08","translateFrame":[{"duration":14,"tweenEasing":0,"x":166.51,"y":-27.37},{"duration":42,"tweenEasing":0,"x":166.51,"y":-27.37},{"duration":4,"x":43.5,"y":-122.69}]},{"name":"cd09","translateFrame":[{"duration":11,"tweenEasing":0,"x":286.75,"y":24.27},{"duration":44,"tweenEasing":0,"x":286.75,"y":24.27},{"duration":5,"x":488.2,"y":2.65}],"rotateFrame":[{"duration":11,"tweenEasing":0,"rotate":35.9},{"duration":44,"tweenEasing":0,"rotate":35.9},{"duration":5,"rotate":-4.29}]}],"slot":[{"name":"cd01","colorFrame":[{"duration":14,"tweenEasing":0,"value":{"aM":0}},{"duration":42,"tweenEasing":0},{"duration":4,"tweenEasing":0},{"duration":0,"value":{"aM":0}}]},{"name":"cd02","colorFrame":[{"duration":33,"tweenEasing":0},{"duration":27,"value":{"aM":0}}]},{"name":"cd03","colorFrame":[{"duration":56,"tweenEasing":0},{"duration":4,"value":{"aM":0}}]},{"name":"cd04","colorFrame":[{"duration":34,"tweenEasing":0},{"duration":26,"value":{"aM":0}}]},{"name":"cd05","colorFrame":[{"duration":54,"tweenEasing":0},{"duration":6,"value":{"aM":0}}]},{"name":"cd06","colorFrame":[{"tweenEasing":0,"value":{"aM":0}},{"duration":49,"tweenEasing":0},{"duration":2,"tweenEasing":0},{"duration":8,"value":{"aM":0}}]},{"name":"cd07","colorFrame":[{"duration":12,"tweenEasing":0,"value":{"aM":0}},{"duration":3,"tweenEasing":0,"value":{"aM":0}},{"duration":43,"tweenEasing":0},{"duration":2,"tweenEasing":0},{"duration":0,"value":{"aM":0}}]},{"name":"cd011","colorFrame":[{"duration":13,"tweenEasing":0,"value":{"aM":0}},{"duration":2,"tweenEasing":0,"value":{"aM":0}},{"duration":40,"tweenEasing":0},{"duration":5,"tweenEasing":0},{"duration":0,"value":{"aM":0}}]},{"name":"cd041","colorFrame":[{"duration":10,"tweenEasing":0,"value":{"aM":0}},{"duration":3,"tweenEasing":0,"value":{"aM":0}},{"duration":41,"tweenEasing":0},{"duration":3,"tweenEasing":0},{"duration":3,"value":{"aM":0}}]}]}],"defaultActions":[{"gotoAndPlay":"newAnimation"}]}]}